{
  "global": {
    "White Dirty": {
      "value": "#f9f9f9",
      "type": "color"
    },
    "White Dirty Border": {
      "value": "#eeeeee",
      "type": "color"
    },
    "Gray 1": {
      "value": "#212932",
      "type": "color"
    },
    "Green Dark 2": {
      "value": "#404c5c",
      "type": "color"
    },
    "Green Dark 1": {
      "value": "#355c6a",
      "type": "color"
    },
    "Green": {
      "value": "#0d999e",
      "type": "color"
    },
    "Green Light": {
      "value": "#e7f5f5",
      "type": "color"
    },
    "Red": {
      "value": "#eb5757",
      "type": "color"
    },
    "Red Light": {
      "value": "#fbeae9",
      "type": "color"
    },
    "Orange": {
      "value": "#f08727",
      "type": "color"
    },
    "Orange Light": {
      "value": "#fef3e9",
      "type": "color"
    },
    "Blue": {
      "value": "#007bbd",
      "type": "color"
    },
    "Blue Light": {
      "value": "#e6f2f8",
      "type": "color"
    },
    "Blue Pale": {
      "value": "#f2f3f7",
      "type": "color"
    },
    "Blue Bright": {
      "value": "#318dff",
      "type": "color"
    },
    "Purple": {
      "value": "#7153c6",
      "type": "color"
    },
    "Purple Light": {
      "value": "#f1eef9",
      "type": "color"
    },
    "Yellow": {
      "value": "#fcdb17",
      "type": "color"
    },
    "Black Main": {
      "value": "#06101a",
      "type": "color"
    },
    "Grey Main": {
      "value": "#767676",
      "type": "color"
    },
    "Grey Main Dim": {
      "value": "#bababa",
      "type": "color"
    },
    "Grey Blue Mid": {
      "value": "#8e9fc8",
      "type": "color"
    },
    "Green Shiny": {
      "value": "#00c2ce",
      "type": "color"
    },
    "Green Terminal": {
      "value": "#5fffd7",
      "type": "color"
    },
    "Greyscale Dark 100": {
      "value": "#788187",
      "type": "color"
    },
    "Greyscale Dark 200": {
      "value": "#484d51",
      "type": "color"
    },
    "Greyscale Dark 300": {
      "value": "#3e4347",
      "type": "color"
    },
    "Greyscale Dark 400": {
      "value": "#323639",
      "type": "color"
    },
    "Greyscale Dark 500": {
      "value": "#282c2f",
      "type": "color"
    },
    "Greyscale Dark 600": {
      "value": "#1e2224",
      "type": "color"
    },
    "Greyscale Dark 700": {
      "value": "#151819",
      "type": "color"
    },
    "Black": {
      "value": "#000000",
      "type": "color"
    },
    "Greyscale Light 100": {
      "value": "#fafafa",
      "type": "color"
    },
    "Greyscale Light 200": {
      "value": "#f1f3f3",
      "type": "color"
    },
    "Greyscale Light 300": {
      "value": "#e9ebec",
      "type": "color"
    },
    "Greyscale Light 400": {
      "value": "#dfe1e2",
      "type": "color"
    },
    "Greyscale Light 500": {
      "value": "#c9cdcf",
      "type": "color"
    },
    "Greyscale Light 600": {
      "value": "#aeb4b7",
      "type": "color"
    },
    "Greyscale Light 700": {
      "value": "#939b9f",
      "type": "color"
    },
    "Greyscale Light 800": {
      "value": "#868e93",
      "type": "color"
    },
    "Magenta": {
      "value": "#e549ff",
      "type": "color"
    },
    "Green Hovered": {
      "value": "#00b2bd",
      "type": "color"
    },
    "Green Pressed": {
      "value": "#009ea8",
      "type": "color"
    },
    "Foundation": {
      "Purple": {
        "purple-50": {
          "value": "#f1eef9",
          "type": "color"
        },
        "purple-100": {
          "value": "#d3caed",
          "type": "color"
        },
        "purple-200": {
          "value": "#beb0e5",
          "type": "color"
        },
        "purple-300": {
          "value": "#a08cd9",
          "type": "color"
        },
        "purple-400": {
          "value": "#8d75d1",
          "type": "color"
        },
        "purple-500": {
          "value": "#7153c6",
          "type": "color"
        },
        "purple-600": {
          "value": "#674cb4",
          "type": "color"
        },
        "purple-700": {
          "value": "#503b8d",
          "type": "color"
        },
        "purple-800": {
          "value": "#3e2e6d",
          "type": "color"
        },
        "purple-900": {
          "value": "#2f2353",
          "type": "color"
        }
      },
      "Green": {
        "green-50": {
          "value": "#e6f9fa",
          "type": "color"
        },
        "green-100": {
          "value": "#b0ecf0",
          "type": "color"
        },
        "green-200": {
          "value": "#8ae3e8",
          "type": "color"
        },
        "green-300": {
          "value": "#54d6de",
          "type": "color"
        },
        "green-400": {
          "value": "#33ced8",
          "type": "color"
        },
        "green-500": {
          "value": "#00c2ce",
          "type": "color"
        },
        "green-600": {
          "value": "#00b1bb",
          "type": "color"
        },
        "green-700": {
          "value": "#008a92",
          "type": "color"
        },
        "green-800": {
          "value": "#006b71",
          "type": "color"
        },
        "green-900": {
          "value": "#005157",
          "type": "color"
        }
      },
      "Blue": {
        "blue-50": {
          "value": "#eaf4ff",
          "type": "color"
        },
        "blue-100": {
          "value": "#bfdcff",
          "type": "color"
        },
        "blue-200": {
          "value": "#a0cbff",
          "type": "color"
        },
        "blue-300": {
          "value": "#75b3ff",
          "type": "color"
        },
        "blue-400": {
          "value": "#5aa4ff",
          "type": "color"
        },
        "blue-500": {
          "value": "#318dff",
          "type": "color"
        },
        "blue-600": {
          "value": "#2d80e8",
          "type": "color"
        },
        "blue-700": {
          "value": "#2364b5",
          "type": "color"
        },
        "blue-800": {
          "value": "#1b4e8c",
          "type": "color"
        },
        "blue-900": {
          "value": "#153b6b",
          "type": "color"
        }
      },
      "Orange": {
        "orange-50": {
          "value": "#fef3e9",
          "type": "color"
        },
        "orange-100": {
          "value": "#fadabc",
          "type": "color"
        },
        "orange-200": {
          "value": "#f8c89c",
          "type": "color"
        },
        "orange-300": {
          "value": "#f5af6e",
          "type": "color"
        },
        "orange-400": {
          "value": "#f39f52",
          "type": "color"
        },
        "orange-500": {
          "value": "#f08727",
          "type": "color"
        },
        "orange-600": {
          "value": "#da7b23",
          "type": "color"
        },
        "orange-700": {
          "value": "#aa601c",
          "type": "color"
        },
        "orange-800": {
          "value": "#844a15",
          "type": "color"
        },
        "orange-900": {
          "value": "#653910",
          "type": "color"
        }
      },
      "Red": {
        "red-50": {
          "value": "#fdeeee",
          "type": "color"
        },
        "red-100": {
          "value": "#f9cbcb",
          "type": "color"
        },
        "red-200": {
          "value": "#f6b2b2",
          "type": "color"
        },
        "red-300": {
          "value": "#f28e8e",
          "type": "color"
        },
        "red-400": {
          "value": "#ef7979",
          "type": "color"
        },
        "red-500": {
          "value": "#eb5757",
          "type": "color"
        },
        "red-600": {
          "value": "#d64f4f",
          "type": "color"
        },
        "red-700": {
          "value": "#a73e3e",
          "type": "color"
        },
        "red-800": {
          "value": "#813030",
          "type": "color"
        },
        "red-900": {
          "value": "#632525",
          "type": "color"
        }
      },
      "Yellow": {
        "yellow-50": {
          "value": "#fffbe8",
          "type": "color"
        },
        "yellow-100": {
          "value": "#fef4b7",
          "type": "color"
        },
        "yellow-200": {
          "value": "#feee94",
          "type": "color"
        },
        "yellow-300": {
          "value": "#fde764",
          "type": "color"
        },
        "yellow-400": {
          "value": "#fde245",
          "type": "color"
        },
        "yellow-500": {
          "value": "#fcdb17",
          "type": "color"
        },
        "yellow-600": {
          "value": "#e5c715",
          "type": "color"
        },
        "yellow-700": {
          "value": "#b39b10",
          "type": "color"
        },
        "yellow-800": {
          "value": "#8b780d",
          "type": "color"
        },
        "yellow-900": {
          "value": "#6a5c0a",
          "type": "color"
        }
      }
    }
  }
}